<?xml version="1.0" encoding="utf-8" ?>
<dwsync>
<file name="bookmark.php" server="ftp.drawalot.com/public_html/demo/" local="129762531403840443" remote="129762529800000000" />
<file name="formsend.php" server="ftp.drawalot.com/public_html/demo/" local="129767161839376859" remote="129767196600000000" />
<file name="thankyou.php" server="ftp.drawalot.com/public_html/demo/" local="129762536092878640" remote="129762534600000000" />
<file name="formsend_bookmark.php" server="ftp.drawalot.com/public_html/demo/" local="129762534826176189" remote="129762533400000000" />
<file name="bookmark.php" server="ftp.drawalot.com/public_html/demo/msg/" local="129762531403840443" remote="129768242400000000" />
<file name="formsend.php" server="ftp.drawalot.com/public_html/demo/msg/" local="129767161839376859" remote="129768242400000000" />
<file name="formsend_bookmark.php" server="ftp.drawalot.com/public_html/demo/msg/" local="129762534826176189" remote="129768242400000000" />
<file name="thankyou.php" server="ftp.drawalot.com/public_html/demo/msg/" local="129775225836744356" remote="129775258200000000" />
<file name="formsend.php" server="drawalot.com/www/demo/msg/" local="129825218259869814" remote="129825253800000000" />
</dwsync>